ServingMachineLearningModels/README.md
ServingMachineLearningModels/__init__.py
ServingMachineLearningModels/__main__.py
ServingMachineLearningModels/file.epub
ServingMachineLearningModels/index.html
ServingMachineLearningModels/css/__init__.py
ServingMachineLearningModels/css/annotations.css
ServingMachineLearningModels/css/main.css
ServingMachineLearningModels/css/normalize.css
ServingMachineLearningModels/css/popup.css
ServingMachineLearningModels/font/__init__.py
ServingMachineLearningModels/font/fontello.eot
ServingMachineLearningModels/font/fontello.svg
ServingMachineLearningModels/font/fontello.ttf
ServingMachineLearningModels/font/fontello.woff
ServingMachineLearningModels/img/__init__.py
ServingMachineLearningModels/img/annotator-glyph-sprite.png
ServingMachineLearningModels/img/annotator-icon-sprite.png
ServingMachineLearningModels/img/apple-touch-icon.png
ServingMachineLearningModels/img/cancelfullscreen.png
ServingMachineLearningModels/img/close.png
ServingMachineLearningModels/img/fullscreen.png
ServingMachineLearningModels/img/loader.gif
ServingMachineLearningModels/img/menu-icon.png
ServingMachineLearningModels/img/save.png
ServingMachineLearningModels/img/saved.png
ServingMachineLearningModels/img/settings-s.png
ServingMachineLearningModels/img/settings.png
ServingMachineLearningModels/img/star.png
ServingMachineLearningModels/js/__init__.py
ServingMachineLearningModels/js/epub.js
ServingMachineLearningModels/js/epub.min.js
ServingMachineLearningModels/js/epub.min.map
ServingMachineLearningModels/js/hooks.min.js
ServingMachineLearningModels/js/hooks.min.map
ServingMachineLearningModels/js/reader.js
ServingMachineLearningModels/js/reader.js.map
ServingMachineLearningModels/js/reader.min.js
ServingMachineLearningModels/js/reader.min.map
ServingMachineLearningModels/js/hooks/__init__.py
ServingMachineLearningModels/js/hooks/extensions/__init__.py
ServingMachineLearningModels/js/hooks/extensions/highlight.js
serving_machine_learning_models-2024.3.2.0.dist-info/METADATA
serving_machine_learning_models-2024.3.2.0.dist-info/WHEEL
serving_machine_learning_models-2024.3.2.0.dist-info/entry_points.txt
serving_machine_learning_models-2024.3.2.0.dist-info/top_level.txt
serving_machine_learning_models-2024.3.2.0.dist-info/RECORD
